staticjinja/__init__.py
staticjinja/__main__.py
staticjinja/cli.py
staticjinja/reloader.py
staticjinja/staticjinja.py
staticjinja-4.1.3.dist-info/entry_points.txt
staticjinja-4.1.3.dist-info/LICENSE
staticjinja-4.1.3.dist-info/WHEEL
staticjinja-4.1.3.dist-info/METADATA
staticjinja-4.1.3.dist-info/RECORD
