Metadata-Version: 2.1
Name: staticjinja
Version: 4.1.3
Summary: jinja based static site generator
Home-page: https://github.com/staticjinja/staticjinja
License: MIT
Keywords: jinja,static,website
Author: Ceasar Bautista
Author-email: cbautista2010@gmail.com
Maintainer: Nick Crews
Maintainer-email: nicholas.b.crews@gmail.com
Requires-Python: >=3.6.2,<4.0.0
Classifier: Development Status :: 5 - Production/Stable
Classifier: Intended Audience :: Developers
Classifier: License :: OSI Approved :: MIT License
Classifier: Operating System :: OS Independent
Classifier: Programming Language :: Python
Classifier: Programming Language :: Python :: 3
Classifier: Programming Language :: Python :: 3.10
Classifier: Programming Language :: Python :: 3.6
Classifier: Programming Language :: Python :: 3.7
Classifier: Programming Language :: Python :: 3.8
Classifier: Programming Language :: Python :: 3.9
Classifier: Topic :: Software Development :: Libraries :: Python Modules
Provides-Extra: dev
Requires-Dist: black (>=21.12b0,<22.0); extra == "dev"
Requires-Dist: docopt-ng (>=0.7.2)
Requires-Dist: easywatch (>=0.0.5,<0.0.6)
Requires-Dist: flake8 (>=3.8.4,<4.0.0); extra == "dev"
Requires-Dist: jinja2 (>=2.10.1)
Requires-Dist: markdown (>=3.3.3,<4.0.0); extra == "dev"
Requires-Dist: pytest (>=6.0.0,<7.0.0); extra == "dev"
Requires-Dist: pytest-check (>=1.0.1,<2.0.0); extra == "dev"
Requires-Dist: pytest-cov (>=2.5,<3.0); extra == "dev"
Requires-Dist: sphinx (>=4.1.1,<5.0.0); extra == "dev"
Requires-Dist: sphinx-rtd-theme (>=0.5.1,<0.6.0); extra == "dev"
Requires-Dist: tomlkit (>=0.5.8,<0.6.0); extra == "dev"
Requires-Dist: tox (>=3.0.0,<4.0.0); extra == "dev"
Requires-Dist: twine (>=3.3.0,<4.0.0); extra == "dev"
Project-URL: Documentation, https://staticjinja.readthedocs.io
Project-URL: Repository, https://github.com/staticjinja/staticjinja
